mico/__init__.py
mico/mi.py
mico/mico.py
mico/mico_utils.py
mico/setup.py
mico/version.py
colin_mico-0.1.0a0.dist-info/LICENSE.txt
colin_mico-0.1.0a0.dist-info/METADATA
colin_mico-0.1.0a0.dist-info/WHEEL
colin_mico-0.1.0a0.dist-info/top_level.txt
colin_mico-0.1.0a0.dist-info/RECORD
