Metadata-Version: 2.1
Name: colin-mico
Version: 0.1.0a0
Summary: MICO: Mutual Information and Conic Optimization for feature selection.
Home-page: https://github.com/jupiters1117/mico
Maintainer: KuoLing Huang
Maintainer-email: jupiters1117@gmail.com
License: BSD
Download-URL: https://github.com/jupiters1117/mico
Platform: UNKNOWN
Classifier: Intended Audience :: Science/Research
Classifier: Intended Audience :: Developers
Classifier: License :: OSI Approved :: BSD License
Classifier: Programming Language :: Python
Classifier: Topic :: Software Development
Classifier: Topic :: Scientific/Engineering
Classifier: Operating System :: Microsoft :: Windows
Classifier: Operating System :: POSIX
Classifier: Operating System :: Unix
Classifier: Operating System :: MacOS
Classifier: Programming Language :: Python :: 3.6
Classifier: Programming Language :: Python :: 3.7
Requires-Dist: scipy (>=1.3.1)
Requires-Dist: numpy (>=1.17.3)
Requires-Dist: scikit-learn (>=0.20.0)
Requires-Dist: joblib (>=0.14.0)
Requires-Dist: psutil (>=5.6.3)
Requires-Dist: pyitlib (>=0.2.2)
Requires-Dist: bottleneck (>=1.0.0)
